fixtool/__init__.py
fixtool/agent.py
fixtool/message.py
fixtool/proxy.py
fixtool/version.py
fixtool-1.0.1.dist-info/DESCRIPTION.rst
fixtool-1.0.1.dist-info/METADATA
fixtool-1.0.1.dist-info/RECORD
fixtool-1.0.1.dist-info/WHEEL
fixtool-1.0.1.dist-info/entry_points.txt
fixtool-1.0.1.dist-info/metadata.json
fixtool-1.0.1.dist-info/top_level.txt
