Metadata-Version: 2.0
Name: fixtool
Version: 1.0.1
Summary: FIX Protocol testing tool
Home-page: https://github.com/da4089/fixtool
Author: David Arnold
Author-email: d+fixtool@0x1.org
License: MIT
Keywords: fix testing
Platform: UNKNOWN
Classifier: Development Status :: 3 - Alpha
Classifier: Topic :: System :: Networking
Classifier: Intended Audience :: Developers
Classifier: License :: OSI Approved :: MIT License
Classifier: Operating System :: OS Independent
Classifier: Programming Language :: Python
Classifier: Programming Language :: Python :: 3.5
Classifier: Programming Language :: Python :: 3.6
Requires-Dist: simplefix (>=1.0.8)
